focal_loss/__init__.py
focal_loss/backend.py
focalloss4keras-0.0.3.dist-info/LICENSE
focalloss4keras-0.0.3.dist-info/METADATA
focalloss4keras-0.0.3.dist-info/WHEEL
focalloss4keras-0.0.3.dist-info/top_level.txt
focalloss4keras-0.0.3.dist-info/RECORD
